tgo/__init__.py
tgo/_tgo.py
tgo/new-joe-kuo-6.21201.gz
tgo/sobol.cc
tgo/sobol.py
tgo-0.1.dist-info/DESCRIPTION.rst
tgo-0.1.dist-info/METADATA
tgo-0.1.dist-info/RECORD
tgo-0.1.dist-info/WHEEL
tgo-0.1.dist-info/metadata.json
tgo-0.1.dist-info/top_level.txt
