Metadata-Version: 2.0
Name: tgo
Version: 0.1
Summary: Topographical global optimisation
Home-page: https://github.com/stefan-endres/tgo
Author: Stefan Endres, Carl Sandrock
Author-email: stefan.c.endres@gmail.com
License: MIT
Keywords: optimization
Platform: UNKNOWN
Classifier: Development Status :: 4 - Beta
Classifier: Intended Audience :: Science/Research
Classifier: Intended Audience :: Developers
Classifier: Topic :: Scientific/Engineering
Classifier: Topic :: Scientific/Engineering :: Mathematics
Classifier: License :: OSI Approved :: MIT License
Classifier: Programming Language :: Python :: 2.7
Classifier: Programming Language :: Python :: 3.5
Classifier: Programming Language :: Python :: 3.6
Requires-Dist: scipy
Requires-Dist: numpy
Requires-Dist: pytest
Requires-Dist: pytest-cov
Provides-Extra: dill support
Requires-Dist: multiprocessing-on-dill; extra == 'dill support'
